gym_racer/__init__.py
gym_racer/envs/__init__.py
gym_racer/envs/racer_car.py
gym_racer/envs/racer_env.py
gym_racer/envs/racer_map.py
gym_racer/envs/utils.py
gym_racer-0.0.2.dist-info/LICENSE.txt
gym_racer-0.0.2.dist-info/METADATA
gym_racer-0.0.2.dist-info/WHEEL
gym_racer-0.0.2.dist-info/top_level.txt
gym_racer-0.0.2.dist-info/RECORD
