Metadata-Version: 2.1
Name: gym-racer
Version: 0.0.2
Summary: OpenAI gym environment of a racing car.
Home-page: https://github.com/Pitrified/gym-racer
Author: Pitrified
Author-email: pitrified.git@gmail.com
License: UNKNOWN
Platform: UNKNOWN
Classifier: Programming Language :: Python :: 3
Classifier: License :: OSI Approved :: MIT License
Classifier: Operating System :: OS Independent
Requires-Python: >=3.6
Requires-Dist: gym
Requires-Dist: pygame
Requires-Dist: numpy
